LICENSE.txt
MANIFEST.in
README.txt
setup.py
docs/HISTORY.rst
lfc_skel/__init__.py
lfc_skel/pastertemplates.py
lfc_skel.egg-info/PKG-INFO
lfc_skel.egg-info/SOURCES.txt
lfc_skel.egg-info/dependency_links.txt
lfc_skel.egg-info/entry_points.txt
lfc_skel.egg-info/not-zip-safe
lfc_skel.egg-info/requires.txt
lfc_skel.egg-info/top_level.txt
lfc_skel/templates/.DS_Store
lfc_skel/templates/lfc_app/.DS_Store
lfc_skel/templates/lfc_app/README.txt_tmpl
lfc_skel/templates/lfc_app/setup.py_tmpl
lfc_skel/templates/lfc_app/+project+/__init__.py_tmpl
lfc_skel/templates/lfc_app/+project+/admin.py_tmpl
lfc_skel/templates/lfc_app/+project+/models.py
lfc_skel/templates/lfc_app/+project+/tests.py_tmpl
lfc_skel/templates/lfc_app/+project+/urls.py_tmpl
lfc_skel/templates/lfc_app/+project+/views.py
lfc_skel/templates/lfc_app/+project+/templates/+project+/template.html
lfc_skel/templates/lfc_app/docs/HISTORY.txt_tmpl